todoterm/__init__.py
todoterm/__main__.py
todoterm/backend.py
todoterm/commands.py
todoterm-1.0.3.dist-info/LICENSE
todoterm-1.0.3.dist-info/METADATA
todoterm-1.0.3.dist-info/WHEEL
todoterm-1.0.3.dist-info/top_level.txt
todoterm-1.0.3.dist-info/RECORD
