Metadata-Version: 2.1
Name: todoterm
Version: 1.0.3
Summary: A simple TODO command line application
Home-page: https://github.com/varajala/todoterm
Author: Valtteri Rajalainen
Author-email: rajalainen.valtteri@gmail.com
License: UNKNOWN
Platform: UNKNOWN
Classifier: Programming Language :: Python :: 3
Classifier: License :: OSI Approved :: MIT License
Classifier: Operating System :: OS Independent
Classifier: Topic :: Software Development
Classifier: Topic :: Utilities
Requires-Python: >=3.7
License-File: LICENSE
